geohex/__init__.py
geohex/geohex.py
py_geohex3-1.0.0.dist-info/DESCRIPTION.rst
py_geohex3-1.0.0.dist-info/METADATA
py_geohex3-1.0.0.dist-info/RECORD
py_geohex3-1.0.0.dist-info/WHEEL
py_geohex3-1.0.0.dist-info/metadata.json
py_geohex3-1.0.0.dist-info/top_level.txt
